freo/__init__.py
freo/main.py
freo-10.1.4.dist-info/METADATA
freo-10.1.4.dist-info/WHEEL
freo-10.1.4.dist-info/top_level.txt
freo-10.1.4.dist-info/RECORD
