Metadata-Version: 2.1
Name: freo
Version: 10.1.4
Summary: This is the almighty freo package
